valer.queue-1.0.3rc11-nspkg.pth
senaite/queue/__init__.py
senaite/queue/api.py
senaite/queue/configure.zcml
senaite/queue/interfaces.py
senaite/queue/pasplugin.py
senaite/queue/queue.py
senaite/queue/request.py
senaite/queue/setuphandlers.py
senaite/queue/version.txt
senaite/queue/adapters/__init__.py
senaite/queue/adapters/actions.py
senaite/queue/adapters/configure.zcml
senaite/queue/adapters/guards.py
senaite/queue/adapters/listing.py
senaite/queue/browser/__init__.py
senaite/queue/browser/configure.zcml
senaite/queue/browser/controlpanel.py
senaite/queue/browser/static/icon.png
senaite/queue/browser/static/queued.gif
senaite/queue/browser/viewlets/__init__.py
senaite/queue/browser/viewlets/configure.zcml
senaite/queue/browser/viewlets/templates/queue_server_status.pt
senaite/queue/browser/viewlets/templates/queued_analyses_sample_viewlet.pt
senaite/queue/browser/viewlets/templates/queued_analyses_viewlet.pt
senaite/queue/browser/views/__init__.py
senaite/queue/browser/views/configure.zcml
senaite/queue/browser/views/tasks.py
senaite/queue/browser/views/worksheet.py
senaite/queue/browser/views/templates/tasks.pt
senaite/queue/client/__init__.py
senaite/queue/client/configure.zcml
senaite/queue/client/consumer.py
senaite/queue/client/routes.py
senaite/queue/client/utility.py
senaite/queue/client/views.py
senaite/queue/locales/senaite.queue.pot
senaite/queue/locales/cs/LC_MESSAGES/senaite.queue.po
senaite/queue/locales/de/LC_MESSAGES/senaite.queue.po
senaite/queue/locales/en/LC_MESSAGES/senaite.queue.po
senaite/queue/locales/es/LC_MESSAGES/senaite.queue.po
senaite/queue/locales/zh_CN/LC_MESSAGES/senaite.queue.po
senaite/queue/monkeys/__init__.py
senaite/queue/monkeys/configure.zcml
senaite/queue/monkeys/browser/__init__.py
senaite/queue/monkeys/browser/worksheet.py
senaite/queue/monkeys/content/__init__.py
senaite/queue/monkeys/content/contact.py
senaite/queue/monkeys/content/worksheet.py
valer.queue-1.0.3rc11.dist-info/DESCRIPTION.rst
valer.queue-1.0.3rc11.dist-info/METADATA
valer.queue-1.0.3rc11.dist-info/RECORD
valer.queue-1.0.3rc11.dist-info/WHEEL
valer.queue-1.0.3rc11.dist-info/entry_points.txt
valer.queue-1.0.3rc11.dist-info/metadata.json
valer.queue-1.0.3rc11.dist-info/namespace_packages.txt
valer.queue-1.0.3rc11.dist-info/top_level.txt
