Metadata-Version: 2.0
Name: valer.queue
Version: 1.0.3rc11
Summary: Asynchronous tasks add-on for VALER LIMS
Home-page: https://github.com/valeriozhang/senaite.queue
Author: Valer Group LLC
Author-email: valerio.zhang@valer.us
License: GPLv2
Keywords: senaite,lims,opensource,valer
Platform: UNKNOWN
Classifier: Framework :: Plone
Classifier: Framework :: Zope2
Classifier: Programming Language :: Python
Classifier: License :: OSI Approved :: GNU General Public License v2 (GPLv2)
Provides-Extra: test
Requires-Dist: cryptography
Requires-Dist: requests
Requires-Dist: setuptools
Requires-Dist: valer.jsonapi (>=1.2.3rc11)
Requires-Dist: valer.lims (>=1.3.4rc11)
Provides-Extra: test
Requires-Dist: Products.PloneTestCase; extra == 'test'
Requires-Dist: Products.SecureMailHost; extra == 'test'
Requires-Dist: plone.app.testing; extra == 'test'
Requires-Dist: unittest2; extra == 'test'
